chikhapo/__init__.py
chikhapo/glottolog_reader.py
chikhapo/loader.py
chikhapo/result_analyzer.py
chikhapo/evaluator/__init__.py
chikhapo/evaluator/bag_of_words_machine_translation.py
chikhapo/evaluator/base.py
chikhapo/evaluator/base_alignments.py
chikhapo/evaluator/evaluator_factory.py
chikhapo/evaluator/translation_conditioned_language_modeling.py
chikhapo/evaluator/word_translation.py
chikhapo/task_feeder/__init__.py
chikhapo/task_feeder/bag_of_words_machine_translation.py
chikhapo/task_feeder/base.py
chikhapo/task_feeder/task_feeder_factory.py
chikhapo/task_feeder/translation_conditioned_language_modeling.py
chikhapo/task_feeder/word_translation.py
chikhapo/task_feeder/word_translation_with_context.py
chikhapo/utils/__init__.py
chikhapo/utils/constants.py
chikhapo/utils/languages.py
chikhapo/utils/parsing.py
chikhapo-0.2.0.dist-info/licenses/LICENSE
chikhapo-0.2.0.dist-info/METADATA
chikhapo-0.2.0.dist-info/WHEEL
chikhapo-0.2.0.dist-info/top_level.txt
chikhapo-0.2.0.dist-info/RECORD
