Metadata-Version: 2.4
Name: chikhapo
Version: 0.2.0
Summary: ChiKhaPo: A Large-Scale Multilingual Benchmark for Evaluating Lexical Comprehension and Generation in Large Language Models
Author-email: Emily Chang <emily.chang@ttic.edu>
License: MIT
Project-URL: Homepage, https://github.com/ec5ug/chikhapo/tree/master/chikhapo_pkg
Project-URL: Issues, https://github.com/ec5ug/chikhapo/issues
Requires-Python: >=3.9
License-File: LICENSE
Requires-Dist: huggingface_hub>=0.23.0
Requires-Dist: fuzzywuzzy>=0.18.0
Requires-Dist: python-Levenshtein>=0.12.0
Requires-Dist: pycountry>=22.3.5
Requires-Dist: nltk>=3.8.1
Requires-Dist: datasets>=2.0.0
Requires-Dist: cmake==4.2.1
Dynamic: license-file
